rqlmongo/__init__.py
rqlmongo/query.py
rqlmongo-0.1.1.dist-info/WHEEL
rqlmongo-0.1.1.dist-info/METADATA
rqlmongo-0.1.1.dist-info/RECORD
